execpeewee/__init__.py
execpeewee/builder.py
execpeewee/handler.py
execpeewee/mapping.py
exec_peewee-0.0.17.dist-info/LICENSE
exec_peewee-0.0.17.dist-info/METADATA
exec_peewee-0.0.17.dist-info/WHEEL
exec_peewee-0.0.17.dist-info/top_level.txt
exec_peewee-0.0.17.dist-info/RECORD
