Metadata-Version: 2.1
Name: exec-peewee
Version: 0.0.17
Summary: Build peewee model class from Mysql.
Home-page: https://github.com/Supplayer/exec_peewee.git
Author: Supplayer
Author-email: x254724521@hotmail.com
License: UNKNOWN
Platform: UNKNOWN
Classifier: Programming Language :: Python :: 3
Classifier: License :: OSI Approved :: MIT License
Classifier: Operating System :: OS Independent
Requires-Python: >=3.6
License-File: LICENSE
Requires-Dist: peewee
Requires-Dist: pymysql
Requires-Dist: cryptography
